summedia/__init__.py
summedia/api.py
summedia/elastic.py
summedia/fetching_data.py
summedia/level.py
summedia/social_media.py
summedia/text.py
summedia/translator.py
tests/__init__.py
tests/test_api.py
tests/test_fetching.py
tests/test_language.py
tests/test_level.py
tests/test_social_media.py
tests/test_text.py
summedia-24.2.3.dist-info/LICENSE
summedia-24.2.3.dist-info/METADATA
summedia-24.2.3.dist-info/WHEEL
summedia-24.2.3.dist-info/top_level.txt
summedia-24.2.3.dist-info/RECORD
