Metadata-Version: 2.1
Name: summedia
Version: 24.2.3
Summary: SumMedia library is a powerful Python package used for extracting and parsing newspaper articles. It simplifies the process of web scraping, article downloading and working with openai API. The plugin enables various functionalities related to news content personalization and categorization.
Home-page: https://github.com/Sebastvin/summedia
Author: Sebastian Malon
Author-email: sebastvin@gmail.com
Project-URL: Bug Tracker, https://github.com/Sebastvin/summedia/issues
Keywords: python openai text article
Classifier: Programming Language :: Python :: 3
Classifier: License :: OSI Approved :: MIT License
Classifier: Operating System :: OS Independent
Requires-Python: >=3.9
License-File: LICENSE
Requires-Dist: openai
Requires-Dist: newspaper3k
Requires-Dist: pycountry
Requires-Dist: requests
Requires-Dist: types-requests
